mito_ai/__init__.py
mito_ai/_version.py
mito_ai/anthropic_client.py
mito_ai/constants.py
mito_ai/gemini_client.py
mito_ai/logger.py
mito_ai/openai_client.py
mito_ai/path_utils.py
mito_ai/provider_manager.py
mito_ai/version_check.py
mito_ai/app_deploy/__init__.py
mito_ai/app_deploy/app_deploy_utils.py
mito_ai/app_deploy/handlers.py
mito_ai/app_deploy/models.py
mito_ai/app_manager/__init__.py
mito_ai/app_manager/handlers.py
mito_ai/app_manager/models.py
mito_ai/app_manager/utils.py
mito_ai/auth/README.md
mito_ai/auth/__init__.py
mito_ai/auth/handlers.py
mito_ai/auth/urls.py
mito_ai/chart_wizard/__init__.py
mito_ai/chart_wizard/handlers.py
mito_ai/chart_wizard/urls.py
mito_ai/chat_history/handlers.py
mito_ai/chat_history/urls.py
mito_ai/completions/handlers.py
mito_ai/completions/message_history.py
mito_ai/completions/models.py
mito_ai/completions/completion_handlers/__init__.py
mito_ai/completions/completion_handlers/agent_auto_error_fixup_handler.py
mito_ai/completions/completion_handlers/agent_execution_handler.py
mito_ai/completions/completion_handlers/chat_completion_handler.py
mito_ai/completions/completion_handlers/code_explain_handler.py
mito_ai/completions/completion_handlers/completion_handler.py
mito_ai/completions/completion_handlers/inline_completer_handler.py
mito_ai/completions/completion_handlers/scratchpad_result_handler.py
mito_ai/completions/completion_handlers/smart_debug_handler.py
mito_ai/completions/completion_handlers/utils.py
mito_ai/completions/prompt_builders/__init__.py
mito_ai/completions/prompt_builders/agent_execution_prompt.py
mito_ai/completions/prompt_builders/agent_smart_debug_prompt.py
mito_ai/completions/prompt_builders/agent_system_message.py
mito_ai/completions/prompt_builders/chart_add_field_prompt.py
mito_ai/completions/prompt_builders/chart_conversion_prompt.py
mito_ai/completions/prompt_builders/chat_name_prompt.py
mito_ai/completions/prompt_builders/chat_prompt.py
mito_ai/completions/prompt_builders/chat_system_message.py
mito_ai-0.1.59.dist-info/METADATA
mito_ai-0.1.59.dist-info/WHEEL
mito_ai-0.1.59.dist-info/entry_points.txt
mito_ai-0.1.59.dist-info/licenses/LICENSE
mito_ai-0.1.59.dist-info/RECORD
