Metadata-Version: 2.4
Name: mito_ai
Version: 0.1.59
Summary: AI chat for JupyterLab
Project-URL: Homepage, https://trymito.io
Project-URL: Bug Tracker, https://github.com/mito-ds/monorepo/issues
Project-URL: Repository, https://github.com/mito-ds/monorepo
Author-email: Aaron Diamond-Reivich <aaron@sagacollab.com>
License: Copyright (c) 2020-2024 Saga Inc.
License-File: LICENSE
Keywords: jupyter,jupyterlab,jupyterlab-extension
Classifier: Framework :: Jupyter
Classifier: Framework :: Jupyter :: JupyterLab
Classifier: Framework :: Jupyter :: JupyterLab :: 4
Classifier: Framework :: Jupyter :: JupyterLab :: Extensions
Classifier: Framework :: Jupyter :: JupyterLab :: Extensions :: Prebuilt
Classifier: License :: OSI Approved :: BSD License
Classifier: Programming Language :: Python
Classifier: Programming Language :: Python :: 3
Classifier: Programming Language :: Python :: 3.9
Classifier: Programming Language :: Python :: 3.10
Classifier: Programming Language :: Python :: 3.11
Classifier: Programming Language :: Python :: 3.12
Classifier: Programming Language :: Python :: 3.13
Requires-Python: >=3.9
Requires-Dist: analytics-python
Requires-Dist: anthropic>=0.6.81
Requires-Dist: google-genai
Requires-Dist: jinja2>=3.0.3
Requires-Dist: jupyterlab<5,>=4.1.0
Requires-Dist: litellm
Requires-Dist: openai>=1.0.0
Requires-Dist: pipreqs
Requires-Dist: pydantic
Requires-Dist: requests>=2.25.0
Requires-Dist: sqlalchemy
Requires-Dist: streamlit
Requires-Dist: tornado>=6.2.0
Requires-Dist: traitlets
Requires-Dist: unidiff
Provides-Extra: deploy
Requires-Dist: hatch-jupyter-builder>=0.5; extra == 'deploy'
Requires-Dist: hatch-nodejs-version>=0.3.2; extra == 'deploy'
Requires-Dist: hatchling>=1.27.0; extra == 'deploy'
Requires-Dist: twine>=4.0.0; extra == 'deploy'
Provides-Extra: test
Requires-Dist: mypy>=1.8.0; extra == 'test'
Requires-Dist: pytest-asyncio==0.25.3; extra == 'test'
Requires-Dist: pytest==8.3.4; extra == 'test'
Requires-Dist: types-requests>=2.25.0; extra == 'test'
Requires-Dist: types-setuptools; extra == 'test'
Requires-Dist: types-tornado>=5.1.1; extra == 'test'
